{
"type": "FeatureCollection",
"name": "Alta Ribagorça",
"crs": { "type": "name", "properties": { "name": "urn:ogc:def:crs:OGC:1.3:CRS84" } },
"features": [
{ "type": "Feature", "properties": { "idequipament": "24595201", "alies": "ZONA ESPORTIVA MUNICIPAL", "nom": "ZONA ESPORTIVA MUNICIPAL", "categoria": "Esports. Lleure|Instal·lacions esportives|Piscina a l'aire lliure| Esports. Lleure|Instal·lacions esportives|Piscina a l'aire lliure| Esports. Lleure|Instal·lacions esportives|Pista| Esports. Lleure|Instal·lacions esportives|Camp|", "tipus_via": "C.", "via": "C. del Riu, s/n, Vall de Boí, la", "sufix_via": "", "num": "s/n", "cpostal": "25527", "poblacio": "Vall de Boí, la", "codi_municipi": "250432", "comarca": "Alta Ribagorça", "telefon1": "973694018", "utmx": "319098", "utmy": "4707989", "data_modificacio": "2025-06-15T07:01:59.000Z", ":@computed_region_wvic_k925": "3", ":@computed_region_bh64_c7uy": "321", "propietats": "Enllaç| <a href=\" http://equipaments.esport.gencat.cat/ceeree/equipaments/19993\" target=\"_blank\">Cens d'equipaments esportius de Catalunya</a><br/>Espais:<br/>1. Piscina a l'aire lliure<br/>2. Piscina a l'aire lliure<br/>3. Pistes poliesportives a l'aire lliure<br/>4. Camps poliespotius i especialitzats", "telefon2": "", "fax": "", "email": "" }, "geometry": { "type": "Point", "coordinates": [ 0.7962946, 42.5013051 ] } },
{ "type": "Feature", "properties": { "idequipament": "24595206", "alies": "ZONA ESPORTIVA MUNICIPAL", "nom": "ZONA ESPORTIVA MUNICIPAL", "categoria": "Esports. Lleure|Instal·lacions esportives|Camp| Esports. Lleure|Instal·lacions esportives|Piscina a l'aire lliure| Esports. Lleure|Instal·lacions esportives|Piscina a l'aire lliure| Esports. Lleure|Instal·lacions esportives|Pista de tennis| Esports. Lleure|Instal·lacions esportives|Altres espais singulars| Esports. Lleure|Instal·lacions esportives|Pista de pàdel| Esports. Lleure|Instal·lacions esportives|Pista|", "tipus_via": "Ctra.", "via": "Ctra. Montanui, s/n, Vilaller", "sufix_via": "", "num": "s/n", "cpostal": "25552", "poblacio": "Vilaller", "codi_municipi": "252458", "comarca": "Alta Ribagorça", "telefon1": "973698147", "utmx": "312028", "utmy": "4704794", "data_modificacio": "2025-06-15T07:01:59.000Z", ":@computed_region_wvic_k925": null, ":@computed_region_bh64_c7uy": null, "propietats": "Enllaç| <a href=\" http://equipaments.esport.gencat.cat/ceeree/equipaments/20021\" target=\"_blank\">Cens d'equipaments esportius de Catalunya</a><br/>Espais:<br/>1. Camps poliespotius i especialitzats<br/>2. Piscina a l'aire lliure<br/>3. Piscina a l'aire lliure<br/>4. Pistes de tennis i mini tennis<br/>5. Altres espais singulars<br/>6. Pistes de pàdel<br/>7. Pistes poliesportives a l'aire lliure", "telefon2": "", "fax": "", "email": "" }, "geometry": { "type": "Point", "coordinates": [ 0.6942088, 42.4657598 ] } },
{ "type": "Feature", "properties": { "idequipament": "24595141", "alies": "PISCINA COBERTA DE PONT DE SUERT", "nom": "PISCINA COBERTA DE PONT DE SUERT", "categoria": "Esports. Lleure|Instal·lacions esportives|Piscina coberta| Esports. Lleure|Instal·lacions esportives|Piscina coberta| Esports. Lleure|Instal·lacions esportives|Sala|", "tipus_via": "C.", "via": "C. del Salencar, s/n, Pont de Suert, el", "sufix_via": "", "num": "s/n", "cpostal": "25520", "poblacio": "Pont de Suert, el", "codi_municipi": "251734", "comarca": "Alta Ribagorça", "telefon1": "973690005", "utmx": "314155", "utmy": "4697135", "data_modificacio": "2025-06-15T07:01:59.000Z", ":@computed_region_wvic_k925": "3", ":@computed_region_bh64_c7uy": "300", "propietats": "Enllaç| <a href=\" http://equipaments.esport.gencat.cat/ceeree/equipaments/19980\" target=\"_blank\">Cens d'equipaments esportius de Catalunya</a><br/>Espais:<br/>1. Piscina coberta<br/>2. Piscina coberta<br/>3. Sales d'activitats i especialitzades", "telefon2": "", "fax": "", "email": "" }, "geometry": { "type": "Point", "coordinates": [ 0.7407154, 42.4054683 ] } }
]
}
